{
	"class" : {
		"fromPayload:andPaddingLength:" : "jp 6/19/2017 11:07" },
	"instance" : {
		"E" : "jp 6/27/2017 21:20",
		"E:" : "jp 6/27/2017 21:20",
		"flagEndHeaders" : "jp 6/27/2017 21:20",
		"flagEndHeaders:" : "jp 6/19/2017 10:48",
		"flagEndStream" : "jp 6/27/2017 21:21",
		"flagEndStream:" : "jp 6/19/2017 10:48",
		"flagPadded" : "jp 6/27/2017 21:21",
		"flagPadded:" : "jp 6/19/2017 10:48",
		"flagPriority" : "jp 6/27/2017 21:21",
		"flagPriority:" : "jp 6/19/2017 10:48",
		"padding" : "jp 6/27/2017 21:18",
		"padding:" : "jp 6/27/2017 21:18",
		"stream" : "jp 6/27/2017 21:23",
		"stream:" : "jp 6/27/2017 21:23",
		"streamDependency" : "jp 6/27/2017 21:18",
		"streamDependency:" : "jp 6/27/2017 21:18",
		"type" : "jp 6/19/2017 11:02",
		"weight" : "jp 6/27/2017 21:22",
		"weight:" : "jp 6/27/2017 21:22" } }
